COPYING
MANIFEST.in
README.md
requirements-dev.txt
requirements.txt
setup.py
gestionatr/__init__.py
gestionatr/cli.py
gestionatr/defs.py
gestionatr/defs_gas.py
gestionatr/exceptions.py
gestionatr/parser_xml_defs_gas.py
gestionatr/utils.py
gestionatr.egg-info/PKG-INFO
gestionatr.egg-info/SOURCES.txt
gestionatr.egg-info/dependency_links.txt
gestionatr.egg-info/entry_points.txt
gestionatr.egg-info/requires.txt
gestionatr.egg-info/top_level.txt
gestionatr/data/A101.xsd
gestionatr/data/A102.xsd
gestionatr/data/A102e.xsd
gestionatr/data/A103.xsd
gestionatr/data/A104.xsd
gestionatr/data/A105.xsd
gestionatr/data/A1224.xsd
gestionatr/data/A1225.xsd
gestionatr/data/A1226.xsd
gestionatr/data/A1239.xsd
gestionatr/data/A12S25.xsd
gestionatr/data/A1350.xsd
gestionatr/data/A138.xsd
gestionatr/data/A141.xsd
gestionatr/data/A142.xsd
gestionatr/data/A143.xsd
gestionatr/data/A144.xsd
gestionatr/data/A1450.xsd
gestionatr/data/A146.xsd
gestionatr/data/A148.xsd
gestionatr/data/A149.xsd
gestionatr/data/A1550.xsd
gestionatr/data/A15S50.xsd
gestionatr/data/A1945.xsd
gestionatr/data/A20.xsd
gestionatr/data/A202.xsd
gestionatr/data/A203.xsd
gestionatr/data/A204.xsd
gestionatr/data/A205.xsd
gestionatr/data/A21.xsd
gestionatr/data/A219.xsd
gestionatr/data/A238.xsd
gestionatr/data/A241.xsd
gestionatr/data/A242.xsd
gestionatr/data/A243.xsd
gestionatr/data/A244.xsd
gestionatr/data/A246.xsd
gestionatr/data/A248.xsd
gestionatr/data/A249.xsd
gestionatr/data/A2504.xsd
gestionatr/data/A2505.xsd
gestionatr/data/A2538.xsd
gestionatr/data/A2541.xsd
gestionatr/data/A2542.xsd
gestionatr/data/A2543.xsd
gestionatr/data/A2544.xsd
gestionatr/data/A2548.xsd
gestionatr/data/A2549.xsd
gestionatr/data/A2604.xsd
gestionatr/data/A2605.xsd
gestionatr/data/A2638.xsd
gestionatr/data/A2641.xsd
gestionatr/data/A2642.xsd
gestionatr/data/A2643.xsd
gestionatr/data/A2644.xsd
gestionatr/data/A2648.xsd
gestionatr/data/A2649.xsd
gestionatr/data/A2S02.xsd
gestionatr/data/A2S03.xsd
gestionatr/data/A2S41.xsd
gestionatr/data/A2S42.xsd
gestionatr/data/A2S49.xsd
gestionatr/data/A302.xsd
gestionatr/data/A304.xsd
gestionatr/data/A305.xsd
gestionatr/data/A338.xsd
gestionatr/data/A341.xsd
gestionatr/data/A342.xsd
gestionatr/data/A343.xsd
