Metadata-Version: 2.1
Name: gestionatr
Version: 4.6.0
Summary: Llibreria de Gestió ATR
Home-page: http://www.gisce.net
Author: GISCE Enginyeria
Author-email: devel@gisce.net
License: General Public Licence 2
Provides: gestionatr
License-File: COPYING
